{
  "name": "Bluecky",
  "area": "Fossil Falls",
  "difficulty": "difficult",
  "description": "i'm BLUE!!!!! DABABDEE!!!!!!! DABADI!!!!!! (Start in Fossil Falls)",
  "hint": "i'm BLUE!!!!! DABABDEE!!!!!!! DABADI!!!!!! (Start in Fossil Falls)",
  "previous_difficulties": [],
  "wiki_markup": "name = Bluecky\n|character = [[Bluecky.png]]\n|difficulty = Difficult\n|area = [[Fossil Falls]]\n|hint = i'm BLUE!!!!! DABABDEE!!!!!!! DABADI!!!!!! (Start in Fossil Falls)\n",
  "location": "realm:Main Realm/Fossil Falls"
}