{
  "name": "Loading Object",
  "area": "Inverted",
  "difficulty": "terrifying",
  "description": "TBA",
  "hint": "TBA",
  "previous_difficulties": [
    "Remorseless"
  ],
  "wiki_markup": "name=[Loading Object]\n|character=[[File:Loading Object.png]]\n|difficulty=[[File:Terrifying.png]] <span style=\"color:#8b17ff\">'''Terrifying'''</span>\n|area=[[Inverted]]\n|hint=TBA\n|additionalinfo\n|previousdifficulties =\n[[File:Remorseless.png]] <span style=\"color:#2084ff\">'''Remorseless'''</span>\n[[File:Strenuous.png]] <span style=\"color:#4048e5\">'''Strenuous'''</span>\n",
  "location": "realm:Inverted"
}