{
  "name": "Marker",
  "area": "Hotel",
  "difficulty": "effortless",
  "description": "Playing toss the dirt (Hidden at Hotel)",
  "hint": "Playing toss the dirt (Hidden at Hotel)",
  "previous_difficulties": [
    "Easy"
  ],
  "wiki_markup": "name=Marker\n|character=[[File:Marker.png|thumb]]\n|difficulty=[[File:Effortless.png]] <span style=\"color:#17a897\">'''Effortless'''</span>\n|area=[[Hotel]]\n|hint=Playing toss the dirt (Hidden at Hotel)\n|additionalinfo\n|previousdifficulties = [[File:Easy.png]] <span style=\"color:#10da8d\">'''Easy'''</span>\n",
  "location": "realm:Main Realm/Hotel"
}