{
  "name": "Motionless_(Object)",
  "area": "Motionless",
  "difficulty": "remorseless",
  "description": "À̶̛̬̰͉̣̏̓͆͐̉̑͊̒͂̌̚͠A̸̖̺̹̞̝̼͚̤̪͎̜̎͆̀̎͐̓͜A̷̫̫̫͇̰̺̻̭̟̰̲̖̺̪̓͐͊͐̐̂̇́̅́̔͜͠A̴̧͙̟̮͎͕̭̰͛̅̎̔̀A̷͖̳̩̎̾͂A̵̩̙̘̫̗̲̲̻̱̲̔͝A̵͖͈̻̝̙̝͆͠Ą̴͋̈́͑A̶̡̨̨̖̓̄̌A̵̡̢̠͔̗̠̻̜̜͙͈͉͚͈͎͆̈̑̊̌͆A̷̗͇̦̿̇̅͝A̷̩͔̬̪̲̜͉͔̯̠͊͋̄̄̀̕̕͜͝Ȧ̷̡̧̪̥̱̜̳̺̰̜̻̍́͑̑̌͜A̶̳̞͍̠̺̼̠͈̩̤͂̐̅̍̊͐͜ͅA̵̡̦̙̲͖̥͎̤̾̈́̐A̸̖̯̪̩̖͉̫̽͛̌͑̈́͋͊̀̉̾̚̕ͅĀ̸̢͚̗͓̗̙̣̰͓̝̆͗̾A̷̛̤̣͋̾̈̈́̔͠͝Å̶̢̼̤̤͍̩̟͉͚͇̼̗̩͂͗A̶̧̙͔͈͖̘̺̟͊͂͗̄͝Ạ̷͈͔͚̯̘̮̃̿̈́̅̾̽̒͠      (Made by AccountDoesNothing)",
  "hint": "À̶̛̬̰͉̣̏̓͆͐̉̑͊̒͂̌̚͠A̸̖̺̹̞̝̼͚̤̪͎̜̎͆̀̎͐̓͜A̷̫̫̫͇̰̺̻̭̟̰̲̖̺̪̓͐͊͐̐̂̇́̅́̔͜͠A̴̧͙̟̮͎͕̭̰͛̅̎̔̀A̷͖̳̩̎̾͂A̵̩̙̘̫̗̲̲̻̱̲̔͝A̵͖͈̻̝̙̝͆͠Ą̴͋̈́͑A̶̡̨̨̖̓̄̌A̵̡̢̠͔̗̠̻̜̜͙͈͉͚͈͎͆̈̑̊̌͆A̷̗͇̦̿̇̅͝A̷̩͔̬̪̲̜͉͔̯̠͊͋̄̄̀̕̕͜͝Ȧ̷̡̧̪̥̱̜̳̺̰̜̻̍́͑̑̌͜A̶̳̞͍̠̺̼̠͈̩̤͂̐̅̍̊͐͜ͅA̵̡̦̙̲͖̥͎̤̾̈́̐A̸̖̯̪̩̖͉̫̽͛̌͑̈́͋͊̀̉̾̚̕ͅĀ̸̢͚̗͓̗̙̣̰͓̝̆͗̾A̷̛̤̣͋̾̈̈́̔͠͝Å̶̢̼̤̤͍̩̟͉͚͇̼̗̩͂͗A̶̧̙͔͈͖̘̺̟͊͂͗̄͝Ạ̷͈͔͚̯̘̮̃̿̈́̅̾̽̒͠      (Made by AccountDoesNothing)",
  "previous_difficulties": [],
  "wiki_markup": "name=Motionless|character=[[File:Motionless.png]]|difficulty=Remorseless|area=[[Motionless]]|hint=À̶̛̬̰͉̣̏̓͆͐̉̑͊̒͂̌̚͠A̸̖̺̹̞̝̼͚̤̪͎̜̎͆̀̎͐̓͜A̷̫̫̫͇̰̺̻̭̟̰̲̖̺̪̓͐͊͐̐̂̇́̅́̔͜͠A̴̧͙̟̮͎͕̭̰͛̅̎̔̀A̷͖̳̩̎̾͂A̵̩̙̘̫̗̲̲̻̱̲̔͝A̵͖͈̻̝̙̝͆͠Ą̴͋̈́͑A̶̡̨̨̖̓̄̌A̵̡̢̠͔̗̠̻̜̜͙͈͉͚͈͎͆̈̑̊̌͆A̷̗͇̦̿̇̅͝A̷̩͔̬̪̲̜͉͔̯̠͊͋̄̄̀̕̕͜͝Ȧ̷̡̧̪̥̱̜̳̺̰̜̻̍́͑̑̌͜A̶̳̞͍̠̺̼̠͈̩̤͂̐̅̍̊͐͜ͅA̵̡̦̙̲͖̥͎̤̾̈́̐A̸̖̯̪̩̖͉̫̽͛̌͑̈́͋͊̀̉̾̚̕ͅĀ̸̢͚̗͓̗̙̣̰͓̝̆͗̾A̷̛̤̣͋̾̈̈́̔͠͝Å̶̢̼̤̤͍̩̟͉͚͇̼̗̩͂͗A̶̧̙͔͈͖̘̺̟͊͂͗̄͝Ạ̷͈͔͚̯̘̮̃̿̈́̅̾̽̒͠      (Made by AccountDoesNothing)|creator=[https://www.roblox.com",
  "location": "subrealm:Main Realm (Goiky)/Motionless"
}