{
  "realms": [
    {
      "label": "Main Realm",
      "image": "Main Realm Sky.webp",
      "gradient": "-webkit-linear-gradient(#78ff78, #00ff00)",
      "accent": "#ffffff"
    },
    {
      "label": "Inverted",
      "image": "Inverted-realm-image.png",
      "gradient": "-webkit-linear-gradient(#C45508, #EEDC5B)",
      "accent": "#ffffff"
    },
    {
      "label": "Yoyleland",
      "image": "Yoyleland.png",
      "gradient": "-webkit-linear-gradient(#cd58e3, #70287a)",
      "accent": "#ffffff"
    },
    {
      "label": "Level 0",
      "image": "Level0.png",
      "gradient": "-webkit-linear-gradient(#e6d7b8, #d4a574)",
      "accent": "#ffffff"
    },
    {
      "label": "Level 1",
      "image": "Level1.png",
      "gradient": "-webkit-linear-gradient(#d4c4b0, #c4b5a0)",
      "accent": "#ffffff"
    },
    {
      "label": "Level 2",
      "image": "Level2.png",
      "gradient": "-webkit-linear-gradient(#c9b8a8, #b0a090)",
      "accent": "#ffffff"
    },
    {
      "label": "Level 3",
      "image": "Level3.png",
      "gradient": "-webkit-linear-gradient(#a88888, #886868)",
      "accent": "#ffffff"
    },
    {
      "label": "Level 4",
      "image": "Level4.png",
      "gradient": "-webkit-linear-gradient(#6b5454, #4a3a3a)",
      "accent": "#ffffff"
    },
    {
      "label": "Level 153",
      "image": "Level153.png",
      "gradient": "-webkit-linear-gradient(#2a1a1a, #0a0a0a)",
      "accent": "#ffffff"
    },
    {
      "label": "RUN FOR YOUR LIFE",
      "image": "RunForYourLife.png",
      "gradient": "-webkit-linear-gradient(#ff0000, #cc0000)",
      "accent": "#ffffff"
    },
    {
      "label": "stairwell",
      "image": "stairwell.png",
      "gradient": "-webkit-linear-gradient(#8b8b8b, #696969)",
      "accent": "#ffffff"
    },
    {
      "label": "Yoyle Factory",
      "image": "YoylefactoryRealm.png",
      "gradient": "-webkit-linear-gradient(#46515D, #2A3944)",
      "accent": "#ffffff"
    },
    {
      "label": "Classic Paradise",
      "image": "Classic paraside.png",
      "gradient": "-webkit-linear-gradient(#ffb6d9, #ff69b4)",
      "accent": "#ffffff"
    },
    {
      "label": "Evil Forest",
      "image": "EVIL.png",
      "gradient": "-webkit-linear-gradient(#b00000, #5a0000)",
      "accent": "#ffffff"
    },
    {
      "label": "Cherry Grove",
      "image": "Cherry Grove.png",
      "gradient": "-webkit-linear-gradient(#896a2e, #cf973a)",
      "accent": "#ffffff"
    },
    {
      "label": "Barren Desert",
      "image": "Barren Desert Sky.webp",
      "gradient": "-webkit-linear-gradient(#c4a747, #8b7355)",
      "accent": "#ffffff"
    },
    {
      "label": "Frozen World",
      "image": "Darkice.jpg",
      "gradient": "-webkit-linear-gradient(#4dd0e1, #006064)",
      "accent": "#000000"
    },
    {
      "label": "Timber Peaks",
      "image": "Timber Peaks.png",
      "gradient": "-webkit-linear-gradient(#ff6f00, #b34700)",
      "accent": "#ffffff"
    },
    {
      "label": "Midnight Rooftops",
      "image": "Midnight-rooftops.png",
      "gradient": "-webkit-linear-gradient(#050522, #140f4a)",
      "accent": "#ffffff"
    },
    {
      "label": "Magma Canyon",
      "image": "Magma Canyon.png",
      "gradient": "-webkit-linear-gradient(#954116, #e93b14)",
      "accent": "#ffffff"
    },
    {
      "label": "Sakura Serenity",
      "image": "Sakura Serenity.png",
      "gradient": "-webkit-linear-gradient(#b56f8f, #8e4f5f)",
      "accent": "#ffffff"
    },
    {
      "label": "Polluted Marshlands",
      "image": "Leak2.jpg",
      "gradient": "-webkit-linear-gradient(#3d5a3d, #1a3a1a)",
      "accent": "#ffffff"
    },
    {
      "label": "BF1D",
      "image": "BF1D Sky.webp",
      "gradient": "-webkit-linear-gradient(#808080, #404040)",
      "accent": "#ffffff"
    }
  ],
  "subrealms": [
    {
      "parent": "Main Realm (Goiky)",
      "label": "Motionless",
      "image": "Motionless.png",
      "gradient": "-webkit-linear-gradient(#4a4a4a, #2a2a2a)",
      "accent": "#ffffff"
    },
    {
      "parent": "Main Realm (Goiky)",
      "label": "Mythical Forest",
      "image": "Mythical Forest.png",
      "gradient": "-webkit-linear-gradient(#2d5016, #1a3d0a)",
      "accent": "#ffffff"
    },
    {
      "parent": "Main Realm (Goiky)",
      "label": "Nearing The End",
      "image": "NTE.png",
      "gradient": "-webkit-linear-gradient(#8b0000, #4a0000)",
      "accent": "#ffff00"
    },
    {
      "parent": "Main Realm (Goiky)",
      "label": "Nihilism",
      "image": "Nihilism.png",
      "gradient": "-webkit-linear-gradient(#1a1a1a, #000000)",
      "accent": "#00ff00"
    },
    {
      "parent": "Main Realm (Goiky)",
      "label": "peep.",
      "image": "peep.png",
      "gradient": "-webkit-linear-gradient(#87ceeb, #4da6ff)",
      "accent": "#ffffff"
    },
    {
      "parent": "Main Realm (Goiky)",
      "label": "Sanctuary",
      "image": "Sanctuary.png",
      "gradient": "-webkit-linear-gradient(#ffd700, #ffed4e)",
      "accent": "#000000"
    },
    {
      "parent": "Main Realm (Goiky)",
      "label": "Hypostasis (Realm)",
      "image": "Hypostasis.png",
      "gradient": "-webkit-linear-gradient(#9370db, #6a0dad)",
      "accent": "#ffffff"
    },
    {
      "parent": "Main Realm (Goiky)",
      "label": "Storm Of Doom",
      "image": "SoD.png",
      "gradient": "-webkit-linear-gradient(#2c3e50, #1a252f)",
      "accent": "#ffffff"
    },
    {
      "parent": "Main Realm (Goiky)",
      "label": "mooD fo mrotS",
      "image": "mooD fo mrotS.png",
      "gradient": "-webkit-linear-gradient(#ffff00, #ffa500)",
      "accent": "#000000"
    },
    {
      "parent": "Main Realm (Goiky)",
      "label": "Zombie Apocalypse",
      "image": "Zombie Apocalypse.png",
      "gradient": "-webkit-linear-gradient(#556b2f, #2d4a1f)",
      "accent": "#ff0000"
    },
    {
      "parent": "Main Realm (Goiky)",
      "label": "Benevolence",
      "image": "Benevolence.png",
      "gradient": "-webkit-linear-gradient(#ffd700, #fff700)",
      "accent": "#000000"
    },
    {
      "parent": "Yoyleland",
      "label": "Abandonment",
      "image": "Abandonment.png",
      "gradient": "-webkit-linear-gradient(#808080, #404040)",
      "accent": "#ffffff"
    },
    {
      "parent": "The Backrooms",
      "label": "Level 0",
      "image": "Level0.png",
      "gradient": "-webkit-linear-gradient(#e6d7b8, #c9a961)",
      "accent": "#ffffff"
    },
    {
      "parent": "The Backrooms",
      "label": "Level 1",
      "image": "Level1.png",
      "gradient": "-webkit-linear-gradient(#8b7355, #5d4a37)",
      "accent": "#ffffff"
    },
    {
      "parent": "The Backrooms",
      "label": "Level 2",
      "image": "Level2.png",
      "gradient": "-webkit-linear-gradient(#4a4a4a, #2a2a2a)",
      "accent": "#ffffff"
    },
    {
      "parent": "The Backrooms",
      "label": "Level 3",
      "image": "Level3.png",
      "gradient": "-webkit-linear-gradient(#1a1a2e, #0f0f1e)",
      "accent": "#00ff00"
    },
    {
      "parent": "The Backrooms",
      "label": "Level 4",
      "image": "Level4.png",
      "gradient": "-webkit-linear-gradient(#2c3e50, #1a252f)",
      "accent": "#ff0000"
    },
    {
      "parent": "The Backrooms",
      "label": "Level 153",
      "image": "Level153.png",
      "gradient": "-webkit-linear-gradient(#9370db, #6a0dad)",
      "accent": "#ffff00"
    },
    {
      "parent": "The Backrooms",
      "label": "RUN FOR YOUR LIFE",
      "image": "RUN.png",
      "gradient": "-webkit-linear-gradient(#ff0000, #cc0000)",
      "accent": "#ffff00"
    },
    {
      "parent": "The Backrooms",
      "label": "stairwell",
      "image": "stairwell.png",
      "gradient": "-webkit-linear-gradient(#696969, #505050)",
      "accent": "#ffffff"
    },
    {
      "parent": "Yoyle Factory",
      "label": "Basement",
      "image": "Basement.png",
      "gradient": "-webkit-linear-gradient(#0f0f0f, #1a1a2e)",
      "accent": "#e0e0e0"
    },
    {
      "parent": "Classic Paradise",
      "label": "Starter Place",
      "image": "Sp icon.png",
      "gradient": "-webkit-linear-gradient(#87ceeb, #4da6ff)",
      "accent": "#ffffff"
    },
    {
      "parent": "Classic Paradise",
      "label": "Classic Insanity",
      "image": "Leaked.png",
      "gradient": "-webkit-linear-gradient(#8b0000, #4a0000)",
      "accent": "#ffff00"
    },
    {
      "parent": "Classic Paradise",
      "label": "Classic Paradox",
      "image": "Classic Paradox.png",
      "gradient": "-webkit-linear-gradient(#ffd700, #ffed4e)",
      "accent": "#000000"
    },
    {
      "parent": "Evil Forest",
      "label": "Evle Froets",
      "image": "Evle Froets.png",
      "gradient": "-webkit-linear-gradient(#8b0000, #4a0000)",
      "accent": "#ffffff"
    },
    {
      "parent": "Evil Forest",
      "label": "evefdpfroestost",
      "image": "evefdpfroestost.png",
      "gradient": "-webkit-linear-gradient(#1a1a1a, #000000)",
      "accent": "#00ff00"
    },
    {
      "parent": "Evil Forest",
      "label": "Limbo",
      "image": "Limbo.png",
      "gradient": "-webkit-linear-gradient(#4a4a4a, #2a2a2a)",
      "accent": "#ff00ff"
    },
    {
      "parent": "Evil Forest",
      "label": "RUN",
      "image": "RUN Evil.png",
      "gradient": "-webkit-linear-gradient(#ff0000, #cc0000)",
      "accent": "#ffff00"
    },
    {
      "parent": "Midnight Rooftops",
      "label": "Gooey Escape",
      "image": "Gooey Escape.png",
      "gradient": "-webkit-linear-gradient(#90ee90, #32cd32)",
      "accent": "#000000"
    }
  ],
  "areas": [
    {
      "parent": "Main Realm",
      "label": "Candyland",
      "image": "Candyland.png",
      "gradient": "-webkit-linear-gradient(#ff69b4, #ffb6d9)",
      "accent": "#ffffff"
    },
    {
      "parent": "Main Realm",
      "label": "City",
      "image": "City.png",
      "gradient": "-webkit-linear-gradient(#4a4a4a, #1a1a1a)",
      "accent": "#87ceeb"
    },
    {
      "parent": "Main Realm",
      "label": "Classic Roblox",
      "image": "Classic__Roblox.png",
      "gradient": "-webkit-linear-gradient(#ff0000, #0000ff)",
      "accent": "#ffff00"
    },
    {
      "parent": "Main Realm",
      "label": "Desert",
      "image": "Desert.png",
      "gradient": "-webkit-linear-gradient(#daa520, #8b4513)",
      "accent": "#ffffff"
    },
    {
      "parent": "Main Realm",
      "label": "Factory",
      "image": "Factory.png",
      "gradient": "-webkit-linear-gradient(#696969, #2f4f4f)",
      "accent": "#ff6b6b"
    },
    {
      "parent": "Main Realm",
      "label": "Floating Island",
      "image": "Floating_Island.png",
      "gradient": "-webkit-linear-gradient(#87ceeb, #e0ffff)",
      "accent": "#ffffff"
    },
    {
      "parent": "Main Realm",
      "label": "Fossil Falls",
      "image": "Fossil_Falls.png",
      "gradient": "-webkit-linear-gradient(#8b7355, #654321)",
      "accent": "#ffffff"
    },
    {
      "parent": "Main Realm",
      "label": "Goiky",
      "image": "Goiky.png",
      "gradient": "-webkit-linear-gradient(#78ff78, #00ff00)",
      "accent": "#ffffff"
    },
    {
      "parent": "Main Realm",
      "label": "Hotel",
      "image": "Hotel.png",
      "gradient": "-webkit-linear-gradient(#daa520, #ffd700)",
      "accent": "#000000"
    },
    {
      "parent": "Main Realm",
      "label": "Jungle",
      "image": "Jungle.png",
      "gradient": "-webkit-linear-gradient(#228b22, #006400)",
      "accent": "#ffff00"
    },
    {
      "parent": "Main Realm",
      "label": "Number Playground",
      "image": "Number_Playground.png",
      "gradient": "-webkit-linear-gradient(#ff00ff, #00ffff)",
      "accent": "#ffffff"
    },
    {
      "parent": "Main Realm",
      "label": "Snowy",
      "image": "Snowy.png",
      "gradient": "-webkit-linear-gradient(#e0ffff, #4dd0e1)",
      "accent": "#000000"
    },
    {
      "parent": "Main Realm",
      "label": "Tropical Islands",
      "image": "Tropical_Islands.png",
      "gradient": "-webkit-linear-gradient(#00ced1, #ffa500)",
      "accent": "#ffffff"
    },
    {
      "parent": "Main Realm",
      "label": "Warehouse",
      "image": "Warehouse.png",
      "gradient": "-webkit-linear-gradient(#808080, #505050)",
      "accent": "#ffffff"
    }
  ]
}


